match2trilegal.py
match2trilegal-1.0.0b1.data/scripts/match2trilegal
match2trilegal-1.0.0b1.dist-info/DESCRIPTION.rst
match2trilegal-1.0.0b1.dist-info/METADATA
match2trilegal-1.0.0b1.dist-info/RECORD
match2trilegal-1.0.0b1.dist-info/WHEEL
match2trilegal-1.0.0b1.dist-info/metadata.json
match2trilegal-1.0.0b1.dist-info/top_level.txt
