Metadata-Version: 2.0
Name: match2trilegal
Version: 1.0.0b1
Summary: UNKNOWN
Home-page: https://github.com/philrosenfield/match2trilegal
Author: Phil Rosenfield
Author-email: philip.rosenfield@cfa.harvard.edu
License: BSD
Platform: UNKNOWN
Requires-Dist: numpy
